[
  {
    "title": "Wunduniik",
    "description": "This modlist is an heavy \u002B1900 mods list based on my personnal preferences. It improves almost everything from the vanilla game to make it looks more like a 2023 game than a 2011 game. Keep in mind that the list is more like a vanilla rework than a list adding new quests, new lands... Wunduniik is a draconic word meaning \u0022Traveler\u0022. I chose this one as I think that when you travel, you discover new cultures, architectures... things can look a lot different. I think this modlist will provide you the same feeling, because you will almost discover a new game.",
    "author": "Alaxouche",
    "maintainers": [
      "github/Alaxouche"
    ],
    "game": "skyrimspecialedition",
    "official": false,
    "tags": [
      "Unofficial",
      "MCO",
      "Immersion",
      "Remaster",
      "Graphic Focused",
      "realistic combats"
    ],
    "nsfw": false,
    "utility_list": false,
    "image_contains_title": false,
    "force_down": false,
    "links": {
      "image": "https://raw.githubusercontent.com/Alaxouche/Wunduniik/main/Wunduniik-Final.webp",
      "readme": "https://github.com/Alaxouche/Wunduniik#readme",
      "download": "https://authored-files.wabbajack.org/Wunduniik.wabbajack_d090be46-be08-44fe-b15a-49ecf6abceb3",
      "machineURL": "Wunduniik",
      "discordURL": "https://discord.gg/alaxouche-s-skyrim-hub-750268919201398805"
    },
    "download_metadata": {
      "Hash": "tpEgsNKIB/Q=",
      "Size": 2054872767,
      "NumberOfArchives": 2579,
      "SizeOfArchives": 152790869936,
      "NumberOfInstalledFiles": 259081,
      "SizeOfInstalledFiles": 207185328421
    },
    "version": "1.3.31",
    "dateCreated": "1970-01-01T00:00:00Z",
    "dateUpdated": "2023-05-28T10:13:21.8708744Z",
    "repositoryName": ""
  }
]